setup.cfg
setup.py
a10ctl/__init__.py
a10ctl/cli.py
a10ctl/command.py
a10ctl.egg-info/PKG-INFO
a10ctl.egg-info/SOURCES.txt
a10ctl.egg-info/dependency_links.txt
a10ctl.egg-info/entry_points.txt
a10ctl.egg-info/requires.txt
a10ctl.egg-info/top_level.txt
acos_client/__init__.py
acos_client/client.py
acos_client/errors.py
acos_client/hash.py
acos_client/logutils.py
acos_client/multipart.py
acos_client/version.py
acos_client/tests/__init__.py
acos_client/tests/t.py
acos_client/tests/unit/__init__.py
acos_client/tests/unit/test_client.py
acos_client/tests/unit/test_cookie.py
acos_client/tests/unit/test_ha.py
acos_client/tests/unit/test_hash.py
acos_client/tests/unit/test_hm.py
acos_client/tests/unit/test_interfaces.py
acos_client/tests/unit/test_logutils.py
acos_client/tests/unit/test_member.py
acos_client/tests/unit/test_partition.py
acos_client/tests/unit/test_server.py
acos_client/tests/unit/test_service_group.py
acos_client/tests/unit/test_session.py
acos_client/tests/unit/test_sip.py
acos_client/tests/unit/test_system.py
acos_client/tests/unit/test_virtual_port.py
acos_client/tests/unit/test_virtual_server.py
acos_client/tests/unit/v21_mocks.py
acos_client/tests/unit/v30/__init__.py
acos_client/tests/unit/v30/test_dns.py
acos_client/tests/unit/v30/test_interface.py
acos_client/tests/unit/v30/test_license_manager.py
acos_client/tests/unit/v30/test_responses.py
acos_client/tests/unit/v30/test_service_group.py
acos_client/tests/unit/v30/test_sflow.py
acos_client/tests/unit/v30/test_slb_common.py
acos_client/tests/unit/v30/test_virtual_server.py
acos_client/v21/__init__.py
acos_client/v21/action.py
acos_client/v21/admin.py
acos_client/v21/axapi_http.py
acos_client/v21/base.py
acos_client/v21/config_file.py
acos_client/v21/device_info.py
acos_client/v21/dns.py
acos_client/v21/ha.py
acos_client/v21/interface.py
acos_client/v21/license_manager.py
acos_client/v21/log.py
acos_client/v21/nat.py
acos_client/v21/network.py
acos_client/v21/partition.py
acos_client/v21/responses.py
acos_client/v21/session.py
acos_client/v21/sflow.py
acos_client/v21/system.py
acos_client/v21/slb/__init__.py
acos_client/v21/slb/aflex.py
acos_client/v21/slb/class_list.py
