Metadata-Version: 1.1
Name: a10ctl
Version: 0.3.1
Summary: Command line tool managing servers on A10 Network Load Balancer
Home-page: https://github.com/tarunlalwani/a10ctl.git
Author: Tarun Lalwani
Author-email: tarunlalwani@gmail.com
License: UNKNOWN
Download-URL: https://github.com/tarunlalwani/a10ctl/archive/0.3.1.tar.gz
Keywords: a10,a10ctl,load,balancer
Platform: UNKNOWN
